equitable_coloring/.__init__.py.un~
equitable_coloring/.core.py.un~
equitable_coloring/__init__.py
equitable_coloring/__init__.py.orig
equitable_coloring/__init__.py~
equitable_coloring/core.py
equitable_coloring/core.py.orig
equitable_coloring/core.py~
equitable_coloring/utils.py
equitable_coloring-0.1.2.dist-info/DESCRIPTION.rst
equitable_coloring-0.1.2.dist-info/METADATA
equitable_coloring-0.1.2.dist-info/RECORD
equitable_coloring-0.1.2.dist-info/WHEEL
equitable_coloring-0.1.2.dist-info/metadata.json
equitable_coloring-0.1.2.dist-info/top_level.txt
