Metadata-Version: 2.0
Name: equitable-coloring
Version: 0.1.2
Summary: Equitable coloring for networkX graphs.
Home-page: https://github.com/musically-ut/equitable-coloring
Author: Utkarsh Upadhyay
Author-email: musically.ut@gmail.com
License: MIT license
Keywords: graph,coloring,equitable,polynomial-time,algorithm
Platform: UNKNOWN
Classifier: Development Status :: 5 - Production/Stable
Classifier: Intended Audience :: Developers
Classifier: License :: OSI Approved :: MIT License
Classifier: Operating System :: Unix
Classifier: Operating System :: POSIX
Classifier: Operating System :: Microsoft :: Windows
Classifier: Programming Language :: Python
Classifier: Programming Language :: Python :: 2.7
Classifier: Programming Language :: Python :: 3
Classifier: Programming Language :: Python :: 3.4
Classifier: Programming Language :: Python :: 3.5
Classifier: Programming Language :: Python :: 3.6
Classifier: Programming Language :: Python :: Implementation :: CPython
Classifier: Programming Language :: Python :: Implementation :: PyPy
Classifier: Topic :: Utilities
Requires-Dist: networkx (>=2.0)
